{
  "input_text": "The cat looks very",
  "original": [
    {
      "token": ",",
      "score": 32.98334884643555
    },
    {
      "token": "a",
      "score": 27.391048431396484
    },
    {
      "token": "the",
      "score": 25.86396598815918
    },
    {
      "token": "\"",
      "score": 23.976879119873047
    },
    {
      "token": "-",
      "score": 22.981632232666016
    },
    {
      "token": ".",
      "score": 22.240436553955078
    },
    {
      "token": "(",
      "score": 22.177907943725586
    },
    {
      "token": "",
      "score": 22.053993225097656
    },
    {
      "token": "in",
      "score": 21.434717178344727
    },
    {
      "token": "and",
      "score": 21.130794525146484
    },
    {
      "token": "P",
      "score": 20.88210678100586
    },
    {
      "token": "'",
      "score": 20.370922088623047
    },
    {
      "token": "D",
      "score": 19.201520919799805
    },
    {
      "token": "of",
      "score": 18.148662567138672
    },
    {
      "token": "is",
      "score": 17.82271957397461
    }
  ],
  "modified": [
    {
      "token": ",",
      "score": 31.115724563598633
    },
    {
      "token": "a",
      "score": 28.29830551147461
    },
    {
      "token": "the",
      "score": 27.85980796813965
    },
    {
      "token": "-",
      "score": 26.99089241027832
    },
    {
      "token": "\"",
      "score": 26.041793823242188
    },
    {
      "token": ".",
      "score": 24.22510528564453
    },
    {
      "token": "in",
      "score": 23.972314834594727
    },
    {
      "token": "",
      "score": 22.55023956298828
    },
    {
      "token": "(",
      "score": 22.183612823486328
    },
    {
      "token": "and",
      "score": 22.159637451171875
    },
    {
      "token": "P",
      "score": 20.713388442993164
    },
    {
      "token": "'",
      "score": 20.697734832763672
    },
    {
      "token": "D",
      "score": 19.933462142944336
    },
    {
      "token": "more",
      "score": 19.72596549987793
    },
    {
      "token": "of",
      "score": 19.412845611572266
    }
  ]
}