{
  "input_text": "The cat looks very",
  "original": [
    {
      "token": "abilia",
      "score": 13.639726638793945
    },
    {
      "token": "maxwell",
      "score": 11.526778221130371
    },
    {
      "token": "Constructed",
      "score": 9.204975128173828
    },
    {
      "token": "iants",
      "score": 8.456832885742188
    },
    {
      "token": "ModLoader",
      "score": 8.446019172668457
    },
    {
      "token": "ENDED",
      "score": 8.386202812194824
    },
    {
      "token": "acio",
      "score": 8.370834350585938
    },
    {
      "token": "Downloadha",
      "score": 7.499048233032227
    },
    {
      "token": "ukong",
      "score": 7.433780670166016
    },
    {
      "token": "redo",
      "score": 7.206655502319336
    },
    {
      "token": "Orderable",
      "score": 7.148514747619629
    },
    {
      "token": "quickShipAvailable",
      "score": 7.000090599060059
    },
    {
      "token": "dinand",
      "score": 6.872934341430664
    },
    {
      "token": "Oracle",
      "score": 6.780320167541504
    },
    {
      "token": "achelor",
      "score": 6.761660575866699
    }
  ],
  "modified": [
    {
      "token": "honest",
      "score": -18.217449188232422
    },
    {
      "token": "abilia",
      "score": -18.458675384521484
    },
    {
      "token": "real",
      "score": -19.378173828125
    },
    {
      "token": "dazzling",
      "score": -19.59866714477539
    },
    {
      "token": "oso",
      "score": -19.698902130126953
    },
    {
      "token": "televised",
      "score": -20.161645889282227
    },
    {
      "token": "personal",
      "score": -20.28775405883789
    },
    {
      "token": "refined",
      "score": -20.414878845214844
    },
    {
      "token": "unsc",
      "score": -20.457294464111328
    },
    {
      "token": "pract",
      "score": -20.929004669189453
    },
    {
      "token": "acio",
      "score": -21.144807815551758
    },
    {
      "token": "atically",
      "score": -21.198101043701172
    },
    {
      "token": "min",
      "score": -21.952089309692383
    },
    {
      "token": "dem",
      "score": -22.092010498046875
    },
    {
      "token": "lumin",
      "score": -22.19477081298828
    }
  ]
}